glfw.pyi
glfw.cpython-312-x86_64-linux-gnu.so
py_glfw_redux-1.1.0.inc/glad/glad/gl.h
py_glfw_redux-1.1.0.inc/glad/KHR/khrplatform.h
py_glfw_redux-1.1.0.inc/glfw/GLFW/glfw3native.h
py_glfw_redux-1.1.0.inc/glfw/GLFW/glfw3.h
py_glfw_redux-1.1.0.dist-info/top_level.txt
py_glfw_redux-1.1.0.dist-info/LICENSE
py_glfw_redux-1.1.0.dist-info/RECORD
py_glfw_redux-1.1.0.dist-info/METADATA
py_glfw_redux-1.1.0.dist-info/WHEEL
py_glfw_redux.libs/libglfw-8d1fc4ab.so.3.4
py_glfw_redux.libs/libglad-dcf0a554.so
